custolint/__init__.py
custolint/_typing.py
custolint/cli.py
custolint/contributors.py
custolint/coverage.py
custolint/env.py
custolint/flake8.py
custolint/generics.py
custolint/git.py
custolint/log.py
custolint/mypy.py
custolint/pylint.py
custolint-0.4.6.dist-info/LICENSE.rst
custolint-0.4.6.dist-info/METADATA
custolint-0.4.6.dist-info/WHEEL
custolint-0.4.6.dist-info/entry_points.txt
custolint-0.4.6.dist-info/top_level.txt
custolint-0.4.6.dist-info/RECORD
