Metadata-Version: 2.1
Name: custolint
Version: 0.4.6
Summary: Another custom linter layer
License: MIT License
Keywords: static code analysis,linter,python,lint,coverage,flake8
Classifier: Environment :: Console
Classifier: Intended Audience :: Developers
Classifier: Operating System :: OS Independent
Classifier: Programming Language :: Python
Classifier: Programming Language :: Python :: 3
Classifier: Topic :: Software Development :: Debuggers
Classifier: Topic :: Software Development :: Quality Assurance
Classifier: Topic :: Software Development :: Testing
License-File: LICENSE.rst
Requires-Dist: bash ==0.6
Requires-Dist: click ==8.1.3
Requires-Dist: colorlog ==6.7.0
Requires-Dist: pydantic ==1.10.9
Provides-Extra: deploy_to_pip
Requires-Dist: twine ; extra == 'deploy_to_pip'
Requires-Dist: build ; extra == 'deploy_to_pip'
Provides-Extra: dev
Requires-Dist: pytest ; extra == 'dev'
Requires-Dist: pylint ; extra == 'dev'
Requires-Dist: coverage ; extra == 'dev'
Requires-Dist: flake8 ; extra == 'dev'
Requires-Dist: mypy ; extra == 'dev'
Requires-Dist: Sphinx ==5.2.3 ; extra == 'dev'
Requires-Dist: sphinxcontrib-programoutput ==0.17 ; extra == 'dev'
Requires-Dist: isort ==5.12.0 ; extra == 'dev'
Requires-Dist: sphinx-click ==4.4.0 ; extra == 'dev'
